pyats/atslog/__init__.py
pyats/atslog/utils.cpython-310-darwin.so
pyats/log/__init__.py
pyats/log/cisco.cpython-310-darwin.so
pyats/log/colour.cpython-310-darwin.so
pyats/log/utils.cpython-310-darwin.so
pyats/log/warnings.cpython-310-darwin.so
pyats/log/commands/__init__.py
pyats/log/commands/_liveview_internal.cpython-310-darwin.so
pyats/log/commands/archive.cpython-310-darwin.so
pyats/log/commands/archive_manager.cpython-310-darwin.so
pyats/log/commands/liveview.py
pyats/log/commands/local_server.cpython-310-darwin.so
pyats/log/commands/logs.cpython-310-darwin.so
pyats/log/commands/logviewer-api.yaml
pyats/log/commands/server.cpython-310-darwin.so
pyats/log/commands/settings.cpython-310-darwin.so
pyats/log/commands/utils.cpython-310-darwin.so
pyats/log/commands/parser/__init__.py
pyats/log/commands/parser/_base_parser_internal.cpython-310-darwin.so
pyats/log/commands/parser/base_parser.py
pyats/log/commands/parser/kleenex_parser.cpython-310-darwin.so
pyats/log/commands/parser/live.cpython-310-darwin.so
pyats/log/commands/parser/raw_parser.cpython-310-darwin.so
pyats/log/commands/parser/robot_parser.cpython-310-darwin.so
pyats/log/commands/parser/xml_parser.cpython-310-darwin.so
pyats/log/commands/parser/xunit_parser.cpython-310-darwin.so
pyats/log/commands/parser/yaml_parser.cpython-310-darwin.so
pyats/log/commands/static/3rdpartylicenses.txt
pyats/log/commands/static/favicon.ico
pyats/log/commands/static/index.html
pyats/log/commands/static/main.8c041bd70c1effdc3335.js
pyats/log/commands/static/polyfills.84d94c43879079a483ea.js
pyats/log/commands/static/runtime.7b63b9fd40098a2e8207.js
pyats/log/commands/static/styles.166a28e49d15df924287.css
pyats/log/commands/static/assets/fonts/CiscoSans/CiscoSansTT/CiscoSansTT.eot
pyats/log/commands/static/assets/fonts/CiscoSans/CiscoSansTT/CiscoSansTT.ttf
pyats/log/commands/static/assets/fonts/CiscoSans/CiscoSansTT/CiscoSansTT.woff
pyats/log/commands/static/assets/fonts/CiscoSans/CiscoSansTT/CiscoSansTT.woff2
pyats.log-25.9.dist-info/METADATA
pyats.log-25.9.dist-info/WHEEL
pyats.log-25.9.dist-info/entry_points.txt
pyats.log-25.9.dist-info/top_level.txt
pyats.log-25.9.dist-info/RECORD
