Metadata-Version: 2.4
Name: pyats.log
Version: 25.9
Summary: pyATS Log: Logging Format and Utilities
Home-page: https://developer.cisco.com/pyats/
Author: Cisco Systems Inc.
Author-email: pyats-support-ext@cisco.com
License: Apache 2.0
Keywords: pyats log logging formatter
Classifier: Development Status :: 6 - Mature
Classifier: Development Status :: 5 - Production/Stable
Classifier: Environment :: Console
Classifier: Intended Audience :: Developers
Classifier: Intended Audience :: Telecommunications Industry
Classifier: Intended Audience :: Information Technology
Classifier: Intended Audience :: System Administrators
Classifier: License :: OSI Approved :: Apache Software License
Classifier: Operating System :: MacOS
Classifier: Operating System :: POSIX :: Linux
Classifier: Programming Language :: Python :: 3.13
Classifier: Programming Language :: Python :: 3.12
Classifier: Programming Language :: Python :: 3.11
Classifier: Programming Language :: Python :: 3.10
Classifier: Programming Language :: Python :: 3.9
Classifier: Programming Language :: Python :: 3 :: Only
Classifier: Programming Language :: Python :: Implementation :: CPython
Classifier: Topic :: Software Development :: Testing
Classifier: Topic :: Software Development :: Build Tools
Classifier: Topic :: Software Development :: Libraries
Classifier: Topic :: Software Development :: Libraries :: Python Modules
Requires-Python: >=3.8
Requires-Dist: pyats.datastructures<25.10.0,>=25.9.0
Requires-Dist: chardet<5.0.0,>=3.0.4
Requires-Dist: aiohttp<3.7; python_version < "3.6"
Requires-Dist: aiohttp<4.0; python_version >= "3.6"
Requires-Dist: pyyaml
Requires-Dist: python-socketio<5.11.3,>=4.2.0
Requires-Dist: python-engineio<4.10.0,>=3.13.0
Requires-Dist: jinja2
Requires-Dist: aiofiles>=0.6.0
Requires-Dist: async_lru>=1.0.2
Provides-Extra: dev
Requires-Dist: Sphinx; extra == "dev"
Requires-Dist: sphinx-rtd-theme; extra == "dev"
Dynamic: author
Dynamic: author-email
Dynamic: classifier
Dynamic: description
Dynamic: home-page
Dynamic: keywords
Dynamic: license
Dynamic: provides-extra
Dynamic: requires-dist
Dynamic: requires-python
Dynamic: summary
